{
  "unit_id": "1029580",
  "form_id": "1029580",
  "display_name": "[Pride as a Rival] Cui",
  "rarity": "SSR",
  "type": "INT",
  "source_base_url": "https://dokkaninfo.com/cards/1029580",
  "variants": [
    {
      "key": "base",
      "eza": false,
      "step": null,
      "is_super_eza": false,
      "source_url": "https://dokkaninfo.com/cards/1029580?eza=false",
      "release_date": "10/3/2024 1:00:00 AM",
      "timezone": "EDT",
      "eza_release_date": null,
      "obtain_type": "Summonable",
      "kit": {
        "leader_skill": "\"Planet Namek Saga\" Category Ki +2 and HP, ATK & DEF +100%",
        "super_attack": {
          "name": "Dastard Impact",
          "effect": "Raises ATK & DEF for 1 turn; Causes supreme damage to enemy; Lowers ATK"
        },
        "ultra_super_attack": {
          "name": null,
          "effect": null
        },
        "passive_skill": {
          "name": "Risky Lie",
          "effect": "(Forever) Ki +2; (Forever) ATK & DEF 100% up; (Forever) Medium chance of evading enemy's attack; If HP is 50% or less when receiving an attack: Chance of evading enemy's attack 20% up; When attacking: ATK & DEF 100% up; Chance of evading enemy's attack 20% up; When the target enemy is in the following status: or: High chance of launching an additional Super Attack",
          "lines": [
            {
              "text": "Ki +2",
              "context": null,
              "once": false,
              "permanent": true,
              "arrows": [],
              "icons": []
            },
            {
              "text": "ATK & DEF 100% up",
              "context": null,
              "once": false,
              "permanent": true,
              "arrows": [
                "up"
              ],
              "icons": [
                "passive_skill_dialog_arrow01"
              ]
            },
            {
              "text": "Medium chance of evading enemy's attack",
              "context": null,
              "once": false,
              "permanent": true,
              "arrows": [],
              "icons": []
            },
            {
              "text": "Chance of evading enemy's attack 20% up",
              "context": "If HP is 50% or less when receiving an attack",
              "once": false,
              "permanent": false,
              "arrows": [
                "up"
              ],
              "icons": [
                "passive_skill_dialog_arrow01"
              ]
            },
            {
              "text": "ATK & DEF 100% up",
              "context": "When attacking",
              "once": false,
              "permanent": false,
              "arrows": [
                "up"
              ],
              "icons": [
                "passive_skill_dialog_arrow01"
              ]
            },
            {
              "text": "Chance of evading enemy's attack 20% up",
              "context": "When attacking",
              "once": false,
              "permanent": false,
              "arrows": [
                "up"
              ],
              "icons": [
                "passive_skill_dialog_arrow01"
              ]
            },
            {
              "text": "High chance of launching an additional Super Attack",
              "context": "When the target enemy is in the following status: or",
              "once": false,
              "permanent": false,
              "arrows": [],
              "icons": []
            }
          ]
        },
        "transformation": {
          "can_transform": false,
          "condition": null
        },
        "reversible_exchange": {
          "can_exchange": false,
          "condition": null
        },
        "transformation_conditions": null,
        "active_skill": {
          "name": null,
          "effect": null,
          "activation_conditions": null
        },
        "standby_skill": null,
        "finish_skills": [],
        "link_skills": [
          "Brutal Beatdown",
          "Coward",
          "Frieza's Minion",
          "Frieza's Army",
          "Loyalty",
          "Thirst for Conquest"
        ],
        "categories": [
          "Planet Namek Saga",
          "Terrifying Conquerors",
          "Space-Traveling Warriors",
          "Mission Execution"
        ],
        "stats": {
          "Cost": 21,
          "Max Lv": 80,
          "SA Lv": 10,
          "HP": {
            "Base Min": 2018,
            "Base Max": 7071,
            "55%": 8671,
            "100%": 12071
          },
          "ATK": {
            "Base Min": 1988,
            "Base Max": 7336,
            "55%": 8936,
            "100%": 12336
          },
          "DEF": {
            "Base Min": 1022,
            "Base Max": 3567,
            "55%": 5167,
            "100%": 8567
          }
        },
        "domains": []
      },
      "assets": [
        "dokkaninfo.com\\images\\dokkan-info-logo.png",
        "dokkaninfo.com\\assets\\global\\en\\layout\\en\\image\\character\\character_thumb_bg\\cha_base_02_03.png",
        "dokkaninfo.com\\assets\\global\\en\\character\\thumb\\card_1029580_thumb\\card_1029580_thumb.png",
        "dokkaninfo.com\\assets\\global\\en\\layout\\en\\image\\character\\cha_rare_sm_ssr.png",
        "dokkaninfo.com\\assets\\global\\en\\layout\\en\\image\\character\\cha_type_icon_02.png",
        "dokkaninfo.com\\assets\\global\\en\\character\\card\\1029580\\card_1029580_bg.png",
        "dokkaninfo.com\\assets\\global\\en\\character\\card\\1029580\\card_1029580_character.png",
        "dokkaninfo.com\\assets\\global\\en\\character\\card\\1029580\\card_1029580_effect.png",
        "dokkaninfo.com\\assets\\global\\en\\character\\card\\1029580\\card_1029580_cutin.png",
        "dokkaninfo.com\\assets\\global\\en\\layout\\en\\image\\character\\character_thumb_bg\\cha_base_04_04.png",
        "dokkaninfo.com\\assets\\global\\en\\character\\thumb\\card_1031300_thumb\\card_1031300_thumb.png",
        "dokkaninfo.com\\assets\\global\\en\\layout\\en\\image\\character\\cha_rare_sm_ur.png",
        "dokkaninfo.com\\assets\\global\\en\\layout\\en\\image\\character\\cha_type_icon_24.png",
        "dokkaninfo.com\\assets\\global\\en\\layout\\en\\image\\character\\character_thumb_bg\\cha_base_00_04.png",
        "dokkaninfo.com\\assets\\global\\en\\character\\thumb\\card_1028570_thumb\\card_1028570_thumb.png",
        "dokkaninfo.com\\assets\\global\\en\\layout\\en\\image\\character\\cha_type_icon_20.png",
        "dokkaninfo.com\\assets\\global\\en\\character\\thumb\\card_1023770_thumb\\card_1023770_thumb.png",
        "dokkaninfo.com\\assets\\global\\en\\ingame\\banners\\gasha_top_banner_11094.png",
        "dokkaninfo.com\\assets\\global\\en\\ingame\\banners\\gasha_top_banner_11124.png",
        "dokkaninfo.com\\assets\\global\\en\\character\\card\\1029580\\1029580.png",
        "dokkaninfo.com\\assets\\global\\en\\character\\card\\1029580\\card_1029580_circle.png",
        "dokkaninfo.com\\assets\\global\\en\\character\\card\\1029580\\card_1029580_piece.png",
        "dokkaninfo.com\\assets\\global\\en\\character\\card\\1029580\\card_1029580sp_cutin_1.png",
        "dokkaninfo.com\\assets\\global\\en\\character\\card\\1029580\\en\\card_1029580_sp_name.png",
        "dokkaninfo.com\\assets\\global\\en\\character\\card\\1029580\\en\\card_1029580_sp_phrase.png",
        "dokkaninfo.com\\assets\\global\\en\\ingame\\events\\myp_banner_event_zbattle_003.png",
        "dokkaninfo.com\\assets\\global\\en\\ingame\\events\\myp_banner_event_zbattle_004.png",
        "dokkaninfo.com\\assets\\global\\en\\ingame\\events\\myp_banner_event_zbattle_062.png",
        "dokkaninfo.com\\assets\\global\\en\\ingame\\events\\myp_banner_event_zbattle_067.png",
        "dokkaninfo.com\\assets\\global\\en\\ingame\\events\\myp_banner_event_zbattle_078.png",
        "dokkaninfo.com\\assets\\global\\en\\ingame\\events\\myp_banner_event_zbattle_090.png",
        "dokkaninfo.com\\assets\\global\\en\\ingame\\events\\myp_banner_event_zbattle_134.png",
        "dokkaninfo.com\\assets\\global\\en\\ingame\\events\\myp_banner_event_zbattle_138.png",
        "dokkaninfo.com\\assets\\global\\en\\ingame\\events\\myp_banner_event_zbattle_166.png",
        "dokkaninfo.com\\assets\\global\\en\\ingame\\events\\myp_banner_event_zbattle_172.png",
        "dokkaninfo.com\\assets\\global\\en\\ingame\\events\\myp_banner_event_zbattle_177.png",
        "dokkaninfo.com\\assets\\global\\en\\ingame\\events\\myp_banner_event_zbattle_182.png",
        "dokkaninfo.com\\assets\\global\\en\\card_category\\label\\card_category_label_0014_b_on.png",
        "dokkaninfo.com\\assets\\global\\en\\card_category\\label\\card_category_label_0041_b_on.png",
        "dokkaninfo.com\\assets\\global\\en\\card_category\\label\\card_category_label_0062_b_on.png",
        "dokkaninfo.com\\assets\\global\\en\\card_category\\label\\card_category_label_0097_b_on.png",
        "dokkaninfo.com\\assets\\global\\en\\layout\\en\\image\\item\\awaken\\awaken_thumb_bg\\thumb_awaken_bronze.png",
        "dokkaninfo.com\\assets\\global\\en\\item\\awaken\\en\\thumb\\thumb_awaken_items_00003\\thumb_awaken_items_00003.png",
        "dokkaninfo.com\\assets\\global\\en\\layout\\en\\image\\item\\awaken\\awaken_thumb_bg\\thumb_awaken_silver.png",
        "dokkaninfo.com\\assets\\global\\en\\item\\awaken\\en\\thumb\\thumb_awaken_items_00005\\thumb_awaken_items_00005.png",
        "dokkaninfo.com\\assets\\global\\en\\layout\\en\\image\\item\\awaken\\awaken_thumb_bg\\thumb_awaken_gold.png",
        "dokkaninfo.com\\assets\\global\\en\\item\\awaken\\en\\thumb\\thumb_awaken_items_00009\\thumb_awaken_items_00009.png",
        "dokkaninfo.com\\assets\\global\\en\\layout\\en\\image\\item\\awaken\\awaken_thumb_bg\\thumb_awaken_rainbow.png",
        "dokkaninfo.com\\assets\\global\\en\\item\\awaken\\en\\thumb\\thumb_awaken_items_00015\\thumb_awaken_items_00015.png",
        "dokkaninfo.com\\assets\\global\\en\\item\\awaken\\en\\thumb\\thumb_awaken_items_00020\\thumb_awaken_items_00020.png",
        "dokkaninfo.com\\assets\\global\\en\\item\\awaken\\en\\thumb\\thumb_awaken_items_15081\\thumb_awaken_items_15081.png",
        "dokkaninfo.com\\assets\\global\\en\\layout\\en\\image\\character\\character_thumb_bg\\cha_base_02_04.png",
        "dokkaninfo.com\\assets\\global\\en\\character\\thumb\\card_1029590_thumb\\card_1029590_thumb.png",
        "dokkaninfo.com\\assets\\global\\en\\layout\\en\\image\\character\\cha_type_icon_22.png",
        "dokkaninfo.com\\assets\\global\\en\\outgame\\extension\\character_detail\\en\\character_detail\\sp_skill_icon_01.png",
        "dokkaninfo.com\\assets\\global\\en\\ingame\\common\\condition\\st_0001.png",
        "dokkaninfo.com\\assets\\global\\en\\ingame\\common\\condition\\st_0002.png",
        "dokkaninfo.com\\assets\\global\\en\\ingame\\common\\condition\\st_0011.png",
        "dokkaninfo.com\\assets\\global\\en\\layout\\en\\image\\ingame\\battle\\skill_dialog\\passive_skill_dialog_arrow01.png",
        "dokkaninfo.com\\assets\\global\\en\\layout\\en\\image\\ingame\\battle\\skill_dialog\\passive_icon_st_0011.png",
        "dokkaninfo.com\\assets\\global\\en\\layout\\en\\image\\ingame\\battle\\skill_dialog\\passive_icon_st_0012.png",
        "dokkaninfo.com\\assets\\global\\en\\character\\thumb\\card_1028580_thumb\\card_1028580_thumb.png",
        "dokkaninfo.com\\assets\\global\\en\\character\\thumb\\card_1028590_thumb\\card_1028590_thumb.png",
        "dokkaninfo.com\\assets\\global\\en\\layout\\en\\image\\character\\character_thumb_bg\\cha_base_03_01.png",
        "dokkaninfo.com\\assets\\global\\en\\character\\thumb\\card_1000510_thumb\\card_1000510_thumb.png",
        "dokkaninfo.com\\assets\\global\\en\\layout\\en\\image\\character\\cha_rare_sm_r.png",
        "dokkaninfo.com\\assets\\global\\en\\layout\\en\\image\\character\\cha_type_icon_03.png",
        "dokkaninfo.com\\assets\\global\\en\\layout\\en\\image\\character\\character_thumb_bg\\cha_base_04_02.png",
        "dokkaninfo.com\\assets\\global\\en\\character\\thumb\\card_1001050_thumb\\card_1001050_thumb.png",
        "dokkaninfo.com\\assets\\global\\en\\layout\\en\\image\\character\\cha_rare_sm_sr.png",
        "dokkaninfo.com\\assets\\global\\en\\layout\\en\\image\\character\\cha_type_icon_04.png",
        "dokkaninfo.com\\assets\\global\\en\\layout\\en\\image\\character\\character_thumb_bg\\cha_base_04_01.png",
        "dokkaninfo.com\\assets\\global\\en\\character\\thumb\\card_1001290_thumb\\card_1001290_thumb.png",
        "dokkaninfo.com\\assets\\global\\en\\layout\\en\\image\\character\\character_thumb_bg\\cha_base_01_04.png",
        "dokkaninfo.com\\assets\\global\\en\\character\\thumb\\card_1023000_thumb\\card_1023000_thumb.png",
        "dokkaninfo.com\\assets\\global\\en\\layout\\en\\image\\character\\cha_type_icon_21.png",
        "dokkaninfo.com\\assets\\global\\en\\layout\\en\\image\\charamenu\\dokkan\\dok_img_kyokugen.png",
        "dokkaninfo.com\\assets\\global\\en\\layout\\en\\image\\character\\character_thumb_bg\\cha_base_03_03.png",
        "dokkaninfo.com\\assets\\global\\en\\character\\thumb\\card_1023740_thumb\\card_1023740_thumb.png",
        "dokkaninfo.com\\assets\\global\\en\\layout\\en\\image\\character\\character_thumb_bg\\cha_base_03_04.png",
        "dokkaninfo.com\\assets\\global\\en\\character\\thumb\\card_1023750_thumb\\card_1023750_thumb.png",
        "dokkaninfo.com\\assets\\global\\en\\layout\\en\\image\\character\\cha_type_icon_23.png",
        "dokkaninfo.com\\assets\\global\\en\\layout\\en\\image\\character\\character_thumb_bg\\cha_base_01_03.png",
        "dokkaninfo.com\\assets\\global\\en\\character\\thumb\\card_1022990_thumb\\card_1022990_thumb.png",
        "dokkaninfo.com\\assets\\global\\en\\layout\\en\\image\\character\\cha_type_icon_01.png",
        "dokkaninfo.com\\assets\\global\\en\\character\\thumb\\card_1023720_thumb\\card_1023720_thumb.png",
        "dokkaninfo.com\\assets\\global\\en\\character\\thumb\\card_1023730_thumb\\card_1023730_thumb.png",
        "dokkaninfo.com\\assets\\global\\en\\character\\thumb\\card_1018950_thumb\\card_1018950_thumb.png",
        "dokkaninfo.com\\assets\\global\\en\\character\\thumb\\card_1026760_thumb\\card_1026760_thumb.png",
        "dokkaninfo.com\\assets\\global\\en\\character\\thumb\\card_1026770_thumb\\card_1026770_thumb.png",
        "dokkaninfo.com\\assets\\global\\en\\layout\\en\\image\\character\\character_thumb_bg\\cha_base_00_03.png",
        "dokkaninfo.com\\assets\\global\\en\\character\\thumb\\card_1026780_thumb\\card_1026780_thumb.png",
        "dokkaninfo.com\\assets\\global\\en\\layout\\en\\image\\character\\cha_type_icon_00.png",
        "dokkaninfo.com\\assets\\global\\en\\character\\thumb\\card_1026790_thumb\\card_1026790_thumb.png",
        "dokkaninfo.com\\assets\\global\\en\\layout\\en\\image\\character\\character_thumb_bg\\cha_base_02_02.png",
        "dokkaninfo.com\\assets\\global\\en\\character\\thumb\\card_1004820_thumb\\card_1004820_thumb.png",
        "dokkaninfo.com\\assets\\global\\en\\layout\\en\\image\\character\\character_thumb_bg\\cha_base_01_02.png",
        "dokkaninfo.com\\assets\\global\\en\\character\\thumb\\card_1006270_thumb\\card_1006270_thumb.png",
        "dokkaninfo.com\\assets\\global\\en\\character\\thumb\\card_1006280_thumb\\card_1006280_thumb.png",
        "dokkaninfo.com\\assets\\global\\en\\character\\thumb\\card_1006290_thumb\\card_1006290_thumb.png",
        "dokkaninfo.com\\assets\\global\\en\\character\\thumb\\card_1006300_thumb\\card_1006300_thumb.png",
        "dokkaninfo.com\\assets\\global\\en\\layout\\en\\image\\character\\character_thumb_bg\\cha_base_04_03.png",
        "dokkaninfo.com\\assets\\global\\en\\character\\thumb\\card_1006310_thumb\\card_1006310_thumb.png",
        "dokkaninfo.com\\assets\\global\\en\\character\\thumb\\card_1006320_thumb\\card_1006320_thumb.png",
        "dokkaninfo.com\\assets\\global\\en\\character\\thumb\\card_1006640_thumb\\card_1006640_thumb.png",
        "dokkaninfo.com\\assets\\global\\en\\character\\thumb\\card_1001110_thumb\\card_1001110_thumb.png",
        "dokkaninfo.com\\assets\\global\\en\\character\\thumb\\card_1001360_thumb\\card_1001360_thumb.png",
        "dokkaninfo.com\\assets\\global\\en\\character\\thumb\\card_1000720_thumb\\card_1000720_thumb.png",
        "dokkaninfo.com\\images\\venatus.webp"
      ],
      "assets_index": {
        "site": [
          {
            "path": "dokkaninfo.com\\images\\venatus.webp",
            "category": "site",
            "subtype": "ad",
            "card_id": null,
            "locale": null,
            "note": "Ad asset"
          },
          {
            "path": "dokkaninfo.com\\images\\dokkan-info-logo.png",
            "category": "site",
            "subtype": "logo",
            "card_id": null,
            "locale": null,
            "note": "DokkanInfo branding"
          }
        ],
        "ui": [
          {
            "path": "dokkaninfo.com\\assets\\global\\en\\ingame\\common\\condition\\st_0001.png",
            "category": "ui",
            "subtype": "condition_icon",
            "card_id": null,
            "locale": null,
            "note": null
          },
          {
            "path": "dokkaninfo.com\\assets\\global\\en\\ingame\\common\\condition\\st_0002.png",
            "category": "ui",
            "subtype": "condition_icon",
            "card_id": null,
            "locale": null,
            "note": null
          },
          {
            "path": "dokkaninfo.com\\assets\\global\\en\\ingame\\common\\condition\\st_0011.png",
            "category": "ui",
            "subtype": "condition_icon",
            "card_id": null,
            "locale": null,
            "note": null
          },
          {
            "path": "dokkaninfo.com\\assets\\global\\en\\layout\\en\\image\\charamenu\\dokkan\\dok_img_kyokugen.png",
            "category": "ui",
            "subtype": "menu_icon",
            "card_id": null,
            "locale": null,
            "note": null
          },
          {
            "path": "dokkaninfo.com\\assets\\global\\en\\layout\\en\\image\\ingame\\battle\\skill_dialog\\passive_icon_st_0011.png",
            "category": "ui",
            "subtype": "passive_mark",
            "card_id": null,
            "locale": null,
            "note": null
          },
          {
            "path": "dokkaninfo.com\\assets\\global\\en\\layout\\en\\image\\ingame\\battle\\skill_dialog\\passive_icon_st_0012.png",
            "category": "ui",
            "subtype": "passive_mark",
            "card_id": null,
            "locale": null,
            "note": null
          },
          {
            "path": "dokkaninfo.com\\assets\\global\\en\\layout\\en\\image\\ingame\\battle\\skill_dialog\\passive_skill_dialog_arrow01.png",
            "category": "ui",
            "subtype": "passive_mark",
            "card_id": null,
            "locale": null,
            "note": null
          },
          {
            "path": "dokkaninfo.com\\assets\\global\\en\\layout\\en\\image\\character\\cha_rare_sm_r.png",
            "category": "ui",
            "subtype": "rarity_icon",
            "card_id": null,
            "locale": null,
            "note": null
          },
          {
            "path": "dokkaninfo.com\\assets\\global\\en\\layout\\en\\image\\character\\cha_rare_sm_sr.png",
            "category": "ui",
            "subtype": "rarity_icon",
            "card_id": null,
            "locale": null,
            "note": null
          },
          {
            "path": "dokkaninfo.com\\assets\\global\\en\\layout\\en\\image\\character\\cha_rare_sm_ssr.png",
            "category": "ui",
            "subtype": "rarity_icon",
            "card_id": null,
            "locale": null,
            "note": null
          },
          {
            "path": "dokkaninfo.com\\assets\\global\\en\\layout\\en\\image\\character\\cha_rare_sm_ur.png",
            "category": "ui",
            "subtype": "rarity_icon",
            "card_id": null,
            "locale": null,
            "note": null
          },
          {
            "path": "dokkaninfo.com\\assets\\global\\en\\layout\\en\\image\\character\\character_thumb_bg\\cha_base_00_03.png",
            "category": "ui",
            "subtype": "thumb_bg",
            "card_id": null,
            "locale": null,
            "note": null
          },
          {
            "path": "dokkaninfo.com\\assets\\global\\en\\layout\\en\\image\\character\\character_thumb_bg\\cha_base_00_04.png",
            "category": "ui",
            "subtype": "thumb_bg",
            "card_id": null,
            "locale": null,
            "note": null
          },
          {
            "path": "dokkaninfo.com\\assets\\global\\en\\layout\\en\\image\\character\\character_thumb_bg\\cha_base_01_02.png",
            "category": "ui",
            "subtype": "thumb_bg",
            "card_id": null,
            "locale": null,
            "note": null
          },
          {
            "path": "dokkaninfo.com\\assets\\global\\en\\layout\\en\\image\\character\\character_thumb_bg\\cha_base_01_03.png",
            "category": "ui",
            "subtype": "thumb_bg",
            "card_id": null,
            "locale": null,
            "note": null
          },
          {
            "path": "dokkaninfo.com\\assets\\global\\en\\layout\\en\\image\\character\\character_thumb_bg\\cha_base_01_04.png",
            "category": "ui",
            "subtype": "thumb_bg",
            "card_id": null,
            "locale": null,
            "note": null
          },
          {
            "path": "dokkaninfo.com\\assets\\global\\en\\layout\\en\\image\\character\\character_thumb_bg\\cha_base_02_02.png",
            "category": "ui",
            "subtype": "thumb_bg",
            "card_id": null,
            "locale": null,
            "note": null
          },
          {
            "path": "dokkaninfo.com\\assets\\global\\en\\layout\\en\\image\\character\\character_thumb_bg\\cha_base_02_03.png",
            "category": "ui",
            "subtype": "thumb_bg",
            "card_id": null,
            "locale": null,
            "note": null
          },
          {
            "path": "dokkaninfo.com\\assets\\global\\en\\layout\\en\\image\\character\\character_thumb_bg\\cha_base_02_04.png",
            "category": "ui",
            "subtype": "thumb_bg",
            "card_id": null,
            "locale": null,
            "note": null
          },
          {
            "path": "dokkaninfo.com\\assets\\global\\en\\layout\\en\\image\\character\\character_thumb_bg\\cha_base_03_01.png",
            "category": "ui",
            "subtype": "thumb_bg",
            "card_id": null,
            "locale": null,
            "note": null
          },
          {
            "path": "dokkaninfo.com\\assets\\global\\en\\layout\\en\\image\\character\\character_thumb_bg\\cha_base_03_03.png",
            "category": "ui",
            "subtype": "thumb_bg",
            "card_id": null,
            "locale": null,
            "note": null
          },
          {
            "path": "dokkaninfo.com\\assets\\global\\en\\layout\\en\\image\\character\\character_thumb_bg\\cha_base_03_04.png",
            "category": "ui",
            "subtype": "thumb_bg",
            "card_id": null,
            "locale": null,
            "note": null
          },
          {
            "path": "dokkaninfo.com\\assets\\global\\en\\layout\\en\\image\\character\\character_thumb_bg\\cha_base_04_01.png",
            "category": "ui",
            "subtype": "thumb_bg",
            "card_id": null,
            "locale": null,
            "note": null
          },
          {
            "path": "dokkaninfo.com\\assets\\global\\en\\layout\\en\\image\\character\\character_thumb_bg\\cha_base_04_02.png",
            "category": "ui",
            "subtype": "thumb_bg",
            "card_id": null,
            "locale": null,
            "note": null
          },
          {
            "path": "dokkaninfo.com\\assets\\global\\en\\layout\\en\\image\\character\\character_thumb_bg\\cha_base_04_03.png",
            "category": "ui",
            "subtype": "thumb_bg",
            "card_id": null,
            "locale": null,
            "note": null
          },
          {
            "path": "dokkaninfo.com\\assets\\global\\en\\layout\\en\\image\\character\\character_thumb_bg\\cha_base_04_04.png",
            "category": "ui",
            "subtype": "thumb_bg",
            "card_id": null,
            "locale": null,
            "note": null
          },
          {
            "path": "dokkaninfo.com\\assets\\global\\en\\layout\\en\\image\\character\\cha_type_icon_00.png",
            "category": "ui",
            "subtype": "type_icon",
            "card_id": null,
            "locale": null,
            "note": null
          },
          {
            "path": "dokkaninfo.com\\assets\\global\\en\\layout\\en\\image\\character\\cha_type_icon_01.png",
            "category": "ui",
            "subtype": "type_icon",
            "card_id": null,
            "locale": null,
            "note": null
          },
          {
            "path": "dokkaninfo.com\\assets\\global\\en\\layout\\en\\image\\character\\cha_type_icon_02.png",
            "category": "ui",
            "subtype": "type_icon",
            "card_id": null,
            "locale": null,
            "note": null
          },
          {
            "path": "dokkaninfo.com\\assets\\global\\en\\layout\\en\\image\\character\\cha_type_icon_03.png",
            "category": "ui",
            "subtype": "type_icon",
            "card_id": null,
            "locale": null,
            "note": null
          },
          {
            "path": "dokkaninfo.com\\assets\\global\\en\\layout\\en\\image\\character\\cha_type_icon_04.png",
            "category": "ui",
            "subtype": "type_icon",
            "card_id": null,
            "locale": null,
            "note": null
          },
          {
            "path": "dokkaninfo.com\\assets\\global\\en\\layout\\en\\image\\character\\cha_type_icon_20.png",
            "category": "ui",
            "subtype": "type_icon",
            "card_id": null,
            "locale": null,
            "note": null
          },
          {
            "path": "dokkaninfo.com\\assets\\global\\en\\layout\\en\\image\\character\\cha_type_icon_21.png",
            "category": "ui",
            "subtype": "type_icon",
            "card_id": null,
            "locale": null,
            "note": null
          },
          {
            "path": "dokkaninfo.com\\assets\\global\\en\\layout\\en\\image\\character\\cha_type_icon_22.png",
            "category": "ui",
            "subtype": "type_icon",
            "card_id": null,
            "locale": null,
            "note": null
          },
          {
            "path": "dokkaninfo.com\\assets\\global\\en\\layout\\en\\image\\character\\cha_type_icon_23.png",
            "category": "ui",
            "subtype": "type_icon",
            "card_id": null,
            "locale": null,
            "note": null
          },
          {
            "path": "dokkaninfo.com\\assets\\global\\en\\layout\\en\\image\\character\\cha_type_icon_24.png",
            "category": "ui",
            "subtype": "type_icon",
            "card_id": null,
            "locale": null,
            "note": null
          }
        ],
        "thumbnail": [
          {
            "path": "dokkaninfo.com\\assets\\global\\en\\character\\thumb\\card_1000510_thumb\\card_1000510_thumb.png",
            "category": "thumbnail",
            "subtype": "card_thumb",
            "card_id": "1000510",
            "locale": "en",
            "note": null
          },
          {
            "path": "dokkaninfo.com\\assets\\global\\en\\character\\thumb\\card_1000720_thumb\\card_1000720_thumb.png",
            "category": "thumbnail",
            "subtype": "card_thumb",
            "card_id": "1000720",
            "locale": "en",
            "note": null
          },
          {
            "path": "dokkaninfo.com\\assets\\global\\en\\character\\thumb\\card_1001050_thumb\\card_1001050_thumb.png",
            "category": "thumbnail",
            "subtype": "card_thumb",
            "card_id": "1001050",
            "locale": "en",
            "note": null
          },
          {
            "path": "dokkaninfo.com\\assets\\global\\en\\character\\thumb\\card_1001110_thumb\\card_1001110_thumb.png",
            "category": "thumbnail",
            "subtype": "card_thumb",
            "card_id": "1001110",
            "locale": "en",
            "note": null
          },
          {
            "path": "dokkaninfo.com\\assets\\global\\en\\character\\thumb\\card_1001290_thumb\\card_1001290_thumb.png",
            "category": "thumbnail",
            "subtype": "card_thumb",
            "card_id": "1001290",
            "locale": "en",
            "note": null
          },
          {
            "path": "dokkaninfo.com\\assets\\global\\en\\character\\thumb\\card_1001360_thumb\\card_1001360_thumb.png",
            "category": "thumbnail",
            "subtype": "card_thumb",
            "card_id": "1001360",
            "locale": "en",
            "note": null
          },
          {
            "path": "dokkaninfo.com\\assets\\global\\en\\character\\thumb\\card_1004820_thumb\\card_1004820_thumb.png",
            "category": "thumbnail",
            "subtype": "card_thumb",
            "card_id": "1004820",
            "locale": "en",
            "note": null
          },
          {
            "path": "dokkaninfo.com\\assets\\global\\en\\character\\thumb\\card_1006270_thumb\\card_1006270_thumb.png",
            "category": "thumbnail",
            "subtype": "card_thumb",
            "card_id": "1006270",
            "locale": "en",
            "note": null
          },
          {
            "path": "dokkaninfo.com\\assets\\global\\en\\character\\thumb\\card_1006280_thumb\\card_1006280_thumb.png",
            "category": "thumbnail",
            "subtype": "card_thumb",
            "card_id": "1006280",
            "locale": "en",
            "note": null
          },
          {
            "path": "dokkaninfo.com\\assets\\global\\en\\character\\thumb\\card_1006290_thumb\\card_1006290_thumb.png",
            "category": "thumbnail",
            "subtype": "card_thumb",
            "card_id": "1006290",
            "locale": "en",
            "note": null
          },
          {
            "path": "dokkaninfo.com\\assets\\global\\en\\character\\thumb\\card_1006300_thumb\\card_1006300_thumb.png",
            "category": "thumbnail",
            "subtype": "card_thumb",
            "card_id": "1006300",
            "locale": "en",
            "note": null
          },
          {
            "path": "dokkaninfo.com\\assets\\global\\en\\character\\thumb\\card_1006310_thumb\\card_1006310_thumb.png",
            "category": "thumbnail",
            "subtype": "card_thumb",
            "card_id": "1006310",
            "locale": "en",
            "note": null
          },
          {
            "path": "dokkaninfo.com\\assets\\global\\en\\character\\thumb\\card_1006320_thumb\\card_1006320_thumb.png",
            "category": "thumbnail",
            "subtype": "card_thumb",
            "card_id": "1006320",
            "locale": "en",
            "note": null
          },
          {
            "path": "dokkaninfo.com\\assets\\global\\en\\character\\thumb\\card_1006640_thumb\\card_1006640_thumb.png",
            "category": "thumbnail",
            "subtype": "card_thumb",
            "card_id": "1006640",
            "locale": "en",
            "note": null
          },
          {
            "path": "dokkaninfo.com\\assets\\global\\en\\character\\thumb\\card_1018950_thumb\\card_1018950_thumb.png",
            "category": "thumbnail",
            "subtype": "card_thumb",
            "card_id": "1018950",
            "locale": "en",
            "note": null
          },
          {
            "path": "dokkaninfo.com\\assets\\global\\en\\character\\thumb\\card_1022990_thumb\\card_1022990_thumb.png",
            "category": "thumbnail",
            "subtype": "card_thumb",
            "card_id": "1022990",
            "locale": "en",
            "note": null
          },
          {
            "path": "dokkaninfo.com\\assets\\global\\en\\character\\thumb\\card_1023000_thumb\\card_1023000_thumb.png",
            "category": "thumbnail",
            "subtype": "card_thumb",
            "card_id": "1023000",
            "locale": "en",
            "note": null
          },
          {
            "path": "dokkaninfo.com\\assets\\global\\en\\character\\thumb\\card_1023720_thumb\\card_1023720_thumb.png",
            "category": "thumbnail",
            "subtype": "card_thumb",
            "card_id": "1023720",
            "locale": "en",
            "note": null
          },
          {
            "path": "dokkaninfo.com\\assets\\global\\en\\character\\thumb\\card_1023730_thumb\\card_1023730_thumb.png",
            "category": "thumbnail",
            "subtype": "card_thumb",
            "card_id": "1023730",
            "locale": "en",
            "note": null
          },
          {
            "path": "dokkaninfo.com\\assets\\global\\en\\character\\thumb\\card_1023740_thumb\\card_1023740_thumb.png",
            "category": "thumbnail",
            "subtype": "card_thumb",
            "card_id": "1023740",
            "locale": "en",
            "note": null
          },
          {
            "path": "dokkaninfo.com\\assets\\global\\en\\character\\thumb\\card_1023750_thumb\\card_1023750_thumb.png",
            "category": "thumbnail",
            "subtype": "card_thumb",
            "card_id": "1023750",
            "locale": "en",
            "note": null
          },
          {
            "path": "dokkaninfo.com\\assets\\global\\en\\character\\thumb\\card_1023770_thumb\\card_1023770_thumb.png",
            "category": "thumbnail",
            "subtype": "card_thumb",
            "card_id": "1023770",
            "locale": "en",
            "note": null
          },
          {
            "path": "dokkaninfo.com\\assets\\global\\en\\character\\thumb\\card_1026760_thumb\\card_1026760_thumb.png",
            "category": "thumbnail",
            "subtype": "card_thumb",
            "card_id": "1026760",
            "locale": "en",
            "note": null
          },
          {
            "path": "dokkaninfo.com\\assets\\global\\en\\character\\thumb\\card_1026770_thumb\\card_1026770_thumb.png",
            "category": "thumbnail",
            "subtype": "card_thumb",
            "card_id": "1026770",
            "locale": "en",
            "note": null
          },
          {
            "path": "dokkaninfo.com\\assets\\global\\en\\character\\thumb\\card_1026780_thumb\\card_1026780_thumb.png",
            "category": "thumbnail",
            "subtype": "card_thumb",
            "card_id": "1026780",
            "locale": "en",
            "note": null
          },
          {
            "path": "dokkaninfo.com\\assets\\global\\en\\character\\thumb\\card_1026790_thumb\\card_1026790_thumb.png",
            "category": "thumbnail",
            "subtype": "card_thumb",
            "card_id": "1026790",
            "locale": "en",
            "note": null
          },
          {
            "path": "dokkaninfo.com\\assets\\global\\en\\character\\thumb\\card_1028570_thumb\\card_1028570_thumb.png",
            "category": "thumbnail",
            "subtype": "card_thumb",
            "card_id": "1028570",
            "locale": "en",
            "note": null
          },
          {
            "path": "dokkaninfo.com\\assets\\global\\en\\character\\thumb\\card_1028580_thumb\\card_1028580_thumb.png",
            "category": "thumbnail",
            "subtype": "card_thumb",
            "card_id": "1028580",
            "locale": "en",
            "note": null
          },
          {
            "path": "dokkaninfo.com\\assets\\global\\en\\character\\thumb\\card_1028590_thumb\\card_1028590_thumb.png",
            "category": "thumbnail",
            "subtype": "card_thumb",
            "card_id": "1028590",
            "locale": "en",
            "note": null
          },
          {
            "path": "dokkaninfo.com\\assets\\global\\en\\character\\thumb\\card_1029580_thumb\\card_1029580_thumb.png",
            "category": "thumbnail",
            "subtype": "card_thumb",
            "card_id": "1029580",
            "locale": "en",
            "note": null
          },
          {
            "path": "dokkaninfo.com\\assets\\global\\en\\character\\thumb\\card_1029590_thumb\\card_1029590_thumb.png",
            "category": "thumbnail",
            "subtype": "card_thumb",
            "card_id": "1029590",
            "locale": "en",
            "note": null
          },
          {
            "path": "dokkaninfo.com\\assets\\global\\en\\character\\thumb\\card_1031300_thumb\\card_1031300_thumb.png",
            "category": "thumbnail",
            "subtype": "card_thumb",
            "card_id": "1031300",
            "locale": "en",
            "note": null
          }
        ],
        "card_art": [
          {
            "path": "dokkaninfo.com\\assets\\global\\en\\character\\card\\1029580\\card_1029580_bg.png",
            "category": "card_art",
            "subtype": "bg",
            "card_id": "1029580",
            "locale": "en",
            "note": null
          },
          {
            "path": "dokkaninfo.com\\assets\\global\\en\\character\\card\\1029580\\card_1029580_piece.png",
            "category": "card_art",
            "subtype": "card_asset",
            "card_id": "1029580",
            "locale": "en",
            "note": null
          },
          {
            "path": "dokkaninfo.com\\assets\\global\\en\\character\\card\\1029580\\card_1029580_character.png",
            "category": "card_art",
            "subtype": "character",
            "card_id": "1029580",
            "locale": "en",
            "note": null
          },
          {
            "path": "dokkaninfo.com\\assets\\global\\en\\character\\card\\1029580\\card_1029580_circle.png",
            "category": "card_art",
            "subtype": "circle",
            "card_id": "1029580",
            "locale": "en",
            "note": null
          },
          {
            "path": "dokkaninfo.com\\assets\\global\\en\\character\\card\\1029580\\card_1029580_cutin.png",
            "category": "card_art",
            "subtype": "cutin",
            "card_id": "1029580",
            "locale": "en",
            "note": null
          },
          {
            "path": "dokkaninfo.com\\assets\\global\\en\\character\\card\\1029580\\card_1029580sp_cutin_1.png",
            "category": "card_art",
            "subtype": "cutin",
            "card_id": "1029580",
            "locale": "en",
            "note": null
          },
          {
            "path": "dokkaninfo.com\\assets\\global\\en\\character\\card\\1029580\\card_1029580_effect.png",
            "category": "card_art",
            "subtype": "effect",
            "card_id": "1029580",
            "locale": "en",
            "note": null
          },
          {
            "path": "dokkaninfo.com\\assets\\global\\en\\character\\card\\1029580\\1029580.png",
            "category": "card_art",
            "subtype": "full_card",
            "card_id": "1029580",
            "locale": "en",
            "note": null
          },
          {
            "path": "dokkaninfo.com\\assets\\global\\en\\character\\card\\1029580\\en\\card_1029580_sp_name.png",
            "category": "card_art",
            "subtype": "super_name",
            "card_id": "1029580",
            "locale": "en",
            "note": null
          },
          {
            "path": "dokkaninfo.com\\assets\\global\\en\\character\\card\\1029580\\en\\card_1029580_sp_phrase.png",
            "category": "card_art",
            "subtype": "super_phrase",
            "card_id": "1029580",
            "locale": "en",
            "note": null
          }
        ],
        "other": [
          {
            "path": "dokkaninfo.com\\assets\\global\\en\\ingame\\banners\\gasha_top_banner_11094.png",
            "category": "other",
            "subtype": null,
            "card_id": null,
            "locale": "en",
            "note": null
          },
          {
            "path": "dokkaninfo.com\\assets\\global\\en\\ingame\\banners\\gasha_top_banner_11124.png",
            "category": "other",
            "subtype": null,
            "card_id": null,
            "locale": "en",
            "note": null
          },
          {
            "path": "dokkaninfo.com\\assets\\global\\en\\item\\awaken\\en\\thumb\\thumb_awaken_items_00003\\thumb_awaken_items_00003.png",
            "category": "other",
            "subtype": null,
            "card_id": null,
            "locale": "en",
            "note": null
          },
          {
            "path": "dokkaninfo.com\\assets\\global\\en\\item\\awaken\\en\\thumb\\thumb_awaken_items_00005\\thumb_awaken_items_00005.png",
            "category": "other",
            "subtype": null,
            "card_id": null,
            "locale": "en",
            "note": null
          },
          {
            "path": "dokkaninfo.com\\assets\\global\\en\\item\\awaken\\en\\thumb\\thumb_awaken_items_00009\\thumb_awaken_items_00009.png",
            "category": "other",
            "subtype": null,
            "card_id": null,
            "locale": "en",
            "note": null
          },
          {
            "path": "dokkaninfo.com\\assets\\global\\en\\item\\awaken\\en\\thumb\\thumb_awaken_items_00015\\thumb_awaken_items_00015.png",
            "category": "other",
            "subtype": null,
            "card_id": null,
            "locale": "en",
            "note": null
          },
          {
            "path": "dokkaninfo.com\\assets\\global\\en\\item\\awaken\\en\\thumb\\thumb_awaken_items_00020\\thumb_awaken_items_00020.png",
            "category": "other",
            "subtype": null,
            "card_id": null,
            "locale": "en",
            "note": null
          },
          {
            "path": "dokkaninfo.com\\assets\\global\\en\\item\\awaken\\en\\thumb\\thumb_awaken_items_15081\\thumb_awaken_items_15081.png",
            "category": "other",
            "subtype": null,
            "card_id": null,
            "locale": "en",
            "note": null
          },
          {
            "path": "dokkaninfo.com\\assets\\global\\en\\layout\\en\\image\\item\\awaken\\awaken_thumb_bg\\thumb_awaken_bronze.png",
            "category": "other",
            "subtype": null,
            "card_id": null,
            "locale": "en",
            "note": null
          },
          {
            "path": "dokkaninfo.com\\assets\\global\\en\\layout\\en\\image\\item\\awaken\\awaken_thumb_bg\\thumb_awaken_gold.png",
            "category": "other",
            "subtype": null,
            "card_id": null,
            "locale": "en",
            "note": null
          },
          {
            "path": "dokkaninfo.com\\assets\\global\\en\\layout\\en\\image\\item\\awaken\\awaken_thumb_bg\\thumb_awaken_rainbow.png",
            "category": "other",
            "subtype": null,
            "card_id": null,
            "locale": "en",
            "note": null
          },
          {
            "path": "dokkaninfo.com\\assets\\global\\en\\layout\\en\\image\\item\\awaken\\awaken_thumb_bg\\thumb_awaken_silver.png",
            "category": "other",
            "subtype": null,
            "card_id": null,
            "locale": "en",
            "note": null
          },
          {
            "path": "dokkaninfo.com\\assets\\global\\en\\outgame\\extension\\character_detail\\en\\character_detail\\sp_skill_icon_01.png",
            "category": "other",
            "subtype": null,
            "card_id": null,
            "locale": "en",
            "note": null
          }
        ],
        "event_banner": [
          {
            "path": "dokkaninfo.com\\assets\\global\\en\\ingame\\events\\myp_banner_event_zbattle_003.png",
            "category": "event_banner",
            "subtype": "zbattle",
            "card_id": null,
            "locale": "en",
            "note": null
          },
          {
            "path": "dokkaninfo.com\\assets\\global\\en\\ingame\\events\\myp_banner_event_zbattle_004.png",
            "category": "event_banner",
            "subtype": "zbattle",
            "card_id": null,
            "locale": "en",
            "note": null
          },
          {
            "path": "dokkaninfo.com\\assets\\global\\en\\ingame\\events\\myp_banner_event_zbattle_062.png",
            "category": "event_banner",
            "subtype": "zbattle",
            "card_id": null,
            "locale": "en",
            "note": null
          },
          {
            "path": "dokkaninfo.com\\assets\\global\\en\\ingame\\events\\myp_banner_event_zbattle_067.png",
            "category": "event_banner",
            "subtype": "zbattle",
            "card_id": null,
            "locale": "en",
            "note": null
          },
          {
            "path": "dokkaninfo.com\\assets\\global\\en\\ingame\\events\\myp_banner_event_zbattle_078.png",
            "category": "event_banner",
            "subtype": "zbattle",
            "card_id": null,
            "locale": "en",
            "note": null
          },
          {
            "path": "dokkaninfo.com\\assets\\global\\en\\ingame\\events\\myp_banner_event_zbattle_090.png",
            "category": "event_banner",
            "subtype": "zbattle",
            "card_id": null,
            "locale": "en",
            "note": null
          },
          {
            "path": "dokkaninfo.com\\assets\\global\\en\\ingame\\events\\myp_banner_event_zbattle_134.png",
            "category": "event_banner",
            "subtype": "zbattle",
            "card_id": null,
            "locale": "en",
            "note": null
          },
          {
            "path": "dokkaninfo.com\\assets\\global\\en\\ingame\\events\\myp_banner_event_zbattle_138.png",
            "category": "event_banner",
            "subtype": "zbattle",
            "card_id": null,
            "locale": "en",
            "note": null
          },
          {
            "path": "dokkaninfo.com\\assets\\global\\en\\ingame\\events\\myp_banner_event_zbattle_166.png",
            "category": "event_banner",
            "subtype": "zbattle",
            "card_id": null,
            "locale": "en",
            "note": null
          },
          {
            "path": "dokkaninfo.com\\assets\\global\\en\\ingame\\events\\myp_banner_event_zbattle_172.png",
            "category": "event_banner",
            "subtype": "zbattle",
            "card_id": null,
            "locale": "en",
            "note": null
          },
          {
            "path": "dokkaninfo.com\\assets\\global\\en\\ingame\\events\\myp_banner_event_zbattle_177.png",
            "category": "event_banner",
            "subtype": "zbattle",
            "card_id": null,
            "locale": "en",
            "note": null
          },
          {
            "path": "dokkaninfo.com\\assets\\global\\en\\ingame\\events\\myp_banner_event_zbattle_182.png",
            "category": "event_banner",
            "subtype": "zbattle",
            "card_id": null,
            "locale": "en",
            "note": null
          }
        ],
        "category_label": [
          {
            "path": "dokkaninfo.com\\assets\\global\\en\\card_category\\label\\card_category_label_0014_b_on.png",
            "category": "category_label",
            "subtype": "0014",
            "card_id": null,
            "locale": "en",
            "note": null
          },
          {
            "path": "dokkaninfo.com\\assets\\global\\en\\card_category\\label\\card_category_label_0041_b_on.png",
            "category": "category_label",
            "subtype": "0041",
            "card_id": null,
            "locale": "en",
            "note": null
          },
          {
            "path": "dokkaninfo.com\\assets\\global\\en\\card_category\\label\\card_category_label_0062_b_on.png",
            "category": "category_label",
            "subtype": "0062",
            "card_id": null,
            "locale": "en",
            "note": null
          },
          {
            "path": "dokkaninfo.com\\assets\\global\\en\\card_category\\label\\card_category_label_0097_b_on.png",
            "category": "category_label",
            "subtype": "0097",
            "card_id": null,
            "locale": "en",
            "note": null
          }
        ]
      },
      "form_id": "1029580",
      "rarity": "SSR",
      "type": "INT",
      "display_name": "[Pride as a Rival] Cui",
      "variant_label": "[Pride as a Rival] Cui — Base"
    }
  ],
  "assets": [
    "dokkaninfo.com\\images\\dokkan-info-logo.png",
    "dokkaninfo.com\\assets\\global\\en\\layout\\en\\image\\character\\character_thumb_bg\\cha_base_02_03.png",
    "dokkaninfo.com\\assets\\global\\en\\character\\thumb\\card_1029580_thumb\\card_1029580_thumb.png",
    "dokkaninfo.com\\assets\\global\\en\\layout\\en\\image\\character\\cha_rare_sm_ssr.png",
    "dokkaninfo.com\\assets\\global\\en\\layout\\en\\image\\character\\cha_type_icon_02.png",
    "dokkaninfo.com\\assets\\global\\en\\character\\card\\1029580\\card_1029580_bg.png",
    "dokkaninfo.com\\assets\\global\\en\\character\\card\\1029580\\card_1029580_character.png",
    "dokkaninfo.com\\assets\\global\\en\\character\\card\\1029580\\card_1029580_effect.png",
    "dokkaninfo.com\\assets\\global\\en\\character\\card\\1029580\\card_1029580_cutin.png",
    "dokkaninfo.com\\assets\\global\\en\\layout\\en\\image\\character\\character_thumb_bg\\cha_base_04_04.png",
    "dokkaninfo.com\\assets\\global\\en\\character\\thumb\\card_1031300_thumb\\card_1031300_thumb.png",
    "dokkaninfo.com\\assets\\global\\en\\layout\\en\\image\\character\\cha_rare_sm_ur.png",
    "dokkaninfo.com\\assets\\global\\en\\layout\\en\\image\\character\\cha_type_icon_24.png",
    "dokkaninfo.com\\assets\\global\\en\\layout\\en\\image\\character\\character_thumb_bg\\cha_base_00_04.png",
    "dokkaninfo.com\\assets\\global\\en\\character\\thumb\\card_1028570_thumb\\card_1028570_thumb.png",
    "dokkaninfo.com\\assets\\global\\en\\layout\\en\\image\\character\\cha_type_icon_20.png",
    "dokkaninfo.com\\assets\\global\\en\\character\\thumb\\card_1023770_thumb\\card_1023770_thumb.png",
    "dokkaninfo.com\\assets\\global\\en\\ingame\\banners\\gasha_top_banner_11094.png",
    "dokkaninfo.com\\assets\\global\\en\\ingame\\banners\\gasha_top_banner_11124.png",
    "dokkaninfo.com\\assets\\global\\en\\character\\card\\1029580\\1029580.png",
    "dokkaninfo.com\\assets\\global\\en\\character\\card\\1029580\\card_1029580_circle.png",
    "dokkaninfo.com\\assets\\global\\en\\character\\card\\1029580\\card_1029580_piece.png",
    "dokkaninfo.com\\assets\\global\\en\\character\\card\\1029580\\card_1029580sp_cutin_1.png",
    "dokkaninfo.com\\assets\\global\\en\\character\\card\\1029580\\en\\card_1029580_sp_name.png",
    "dokkaninfo.com\\assets\\global\\en\\character\\card\\1029580\\en\\card_1029580_sp_phrase.png",
    "dokkaninfo.com\\assets\\global\\en\\ingame\\events\\myp_banner_event_zbattle_003.png",
    "dokkaninfo.com\\assets\\global\\en\\ingame\\events\\myp_banner_event_zbattle_004.png",
    "dokkaninfo.com\\assets\\global\\en\\ingame\\events\\myp_banner_event_zbattle_062.png",
    "dokkaninfo.com\\assets\\global\\en\\ingame\\events\\myp_banner_event_zbattle_067.png",
    "dokkaninfo.com\\assets\\global\\en\\ingame\\events\\myp_banner_event_zbattle_078.png",
    "dokkaninfo.com\\assets\\global\\en\\ingame\\events\\myp_banner_event_zbattle_090.png",
    "dokkaninfo.com\\assets\\global\\en\\ingame\\events\\myp_banner_event_zbattle_134.png",
    "dokkaninfo.com\\assets\\global\\en\\ingame\\events\\myp_banner_event_zbattle_138.png",
    "dokkaninfo.com\\assets\\global\\en\\ingame\\events\\myp_banner_event_zbattle_166.png",
    "dokkaninfo.com\\assets\\global\\en\\ingame\\events\\myp_banner_event_zbattle_172.png",
    "dokkaninfo.com\\assets\\global\\en\\ingame\\events\\myp_banner_event_zbattle_177.png",
    "dokkaninfo.com\\assets\\global\\en\\ingame\\events\\myp_banner_event_zbattle_182.png",
    "dokkaninfo.com\\assets\\global\\en\\card_category\\label\\card_category_label_0014_b_on.png",
    "dokkaninfo.com\\assets\\global\\en\\card_category\\label\\card_category_label_0041_b_on.png",
    "dokkaninfo.com\\assets\\global\\en\\card_category\\label\\card_category_label_0062_b_on.png",
    "dokkaninfo.com\\assets\\global\\en\\card_category\\label\\card_category_label_0097_b_on.png",
    "dokkaninfo.com\\assets\\global\\en\\layout\\en\\image\\item\\awaken\\awaken_thumb_bg\\thumb_awaken_bronze.png",
    "dokkaninfo.com\\assets\\global\\en\\item\\awaken\\en\\thumb\\thumb_awaken_items_00003\\thumb_awaken_items_00003.png",
    "dokkaninfo.com\\assets\\global\\en\\layout\\en\\image\\item\\awaken\\awaken_thumb_bg\\thumb_awaken_silver.png",
    "dokkaninfo.com\\assets\\global\\en\\item\\awaken\\en\\thumb\\thumb_awaken_items_00005\\thumb_awaken_items_00005.png",
    "dokkaninfo.com\\assets\\global\\en\\layout\\en\\image\\item\\awaken\\awaken_thumb_bg\\thumb_awaken_gold.png",
    "dokkaninfo.com\\assets\\global\\en\\item\\awaken\\en\\thumb\\thumb_awaken_items_00009\\thumb_awaken_items_00009.png",
    "dokkaninfo.com\\assets\\global\\en\\layout\\en\\image\\item\\awaken\\awaken_thumb_bg\\thumb_awaken_rainbow.png",
    "dokkaninfo.com\\assets\\global\\en\\item\\awaken\\en\\thumb\\thumb_awaken_items_00015\\thumb_awaken_items_00015.png",
    "dokkaninfo.com\\assets\\global\\en\\item\\awaken\\en\\thumb\\thumb_awaken_items_00020\\thumb_awaken_items_00020.png",
    "dokkaninfo.com\\assets\\global\\en\\item\\awaken\\en\\thumb\\thumb_awaken_items_15081\\thumb_awaken_items_15081.png",
    "dokkaninfo.com\\assets\\global\\en\\layout\\en\\image\\character\\character_thumb_bg\\cha_base_02_04.png",
    "dokkaninfo.com\\assets\\global\\en\\character\\thumb\\card_1029590_thumb\\card_1029590_thumb.png",
    "dokkaninfo.com\\assets\\global\\en\\layout\\en\\image\\character\\cha_type_icon_22.png",
    "dokkaninfo.com\\assets\\global\\en\\outgame\\extension\\character_detail\\en\\character_detail\\sp_skill_icon_01.png",
    "dokkaninfo.com\\assets\\global\\en\\ingame\\common\\condition\\st_0001.png",
    "dokkaninfo.com\\assets\\global\\en\\ingame\\common\\condition\\st_0002.png",
    "dokkaninfo.com\\assets\\global\\en\\ingame\\common\\condition\\st_0011.png",
    "dokkaninfo.com\\assets\\global\\en\\layout\\en\\image\\ingame\\battle\\skill_dialog\\passive_skill_dialog_arrow01.png",
    "dokkaninfo.com\\assets\\global\\en\\layout\\en\\image\\ingame\\battle\\skill_dialog\\passive_icon_st_0011.png",
    "dokkaninfo.com\\assets\\global\\en\\layout\\en\\image\\ingame\\battle\\skill_dialog\\passive_icon_st_0012.png",
    "dokkaninfo.com\\assets\\global\\en\\character\\thumb\\card_1028580_thumb\\card_1028580_thumb.png",
    "dokkaninfo.com\\assets\\global\\en\\character\\thumb\\card_1028590_thumb\\card_1028590_thumb.png",
    "dokkaninfo.com\\assets\\global\\en\\layout\\en\\image\\character\\character_thumb_bg\\cha_base_03_01.png",
    "dokkaninfo.com\\assets\\global\\en\\character\\thumb\\card_1000510_thumb\\card_1000510_thumb.png",
    "dokkaninfo.com\\assets\\global\\en\\layout\\en\\image\\character\\cha_rare_sm_r.png",
    "dokkaninfo.com\\assets\\global\\en\\layout\\en\\image\\character\\cha_type_icon_03.png",
    "dokkaninfo.com\\assets\\global\\en\\layout\\en\\image\\character\\character_thumb_bg\\cha_base_04_02.png",
    "dokkaninfo.com\\assets\\global\\en\\character\\thumb\\card_1001050_thumb\\card_1001050_thumb.png",
    "dokkaninfo.com\\assets\\global\\en\\layout\\en\\image\\character\\cha_rare_sm_sr.png",
    "dokkaninfo.com\\assets\\global\\en\\layout\\en\\image\\character\\cha_type_icon_04.png",
    "dokkaninfo.com\\assets\\global\\en\\layout\\en\\image\\character\\character_thumb_bg\\cha_base_04_01.png",
    "dokkaninfo.com\\assets\\global\\en\\character\\thumb\\card_1001290_thumb\\card_1001290_thumb.png",
    "dokkaninfo.com\\assets\\global\\en\\layout\\en\\image\\character\\character_thumb_bg\\cha_base_01_04.png",
    "dokkaninfo.com\\assets\\global\\en\\character\\thumb\\card_1023000_thumb\\card_1023000_thumb.png",
    "dokkaninfo.com\\assets\\global\\en\\layout\\en\\image\\character\\cha_type_icon_21.png",
    "dokkaninfo.com\\assets\\global\\en\\layout\\en\\image\\charamenu\\dokkan\\dok_img_kyokugen.png",
    "dokkaninfo.com\\assets\\global\\en\\layout\\en\\image\\character\\character_thumb_bg\\cha_base_03_03.png",
    "dokkaninfo.com\\assets\\global\\en\\character\\thumb\\card_1023740_thumb\\card_1023740_thumb.png",
    "dokkaninfo.com\\assets\\global\\en\\layout\\en\\image\\character\\character_thumb_bg\\cha_base_03_04.png",
    "dokkaninfo.com\\assets\\global\\en\\character\\thumb\\card_1023750_thumb\\card_1023750_thumb.png",
    "dokkaninfo.com\\assets\\global\\en\\layout\\en\\image\\character\\cha_type_icon_23.png",
    "dokkaninfo.com\\assets\\global\\en\\layout\\en\\image\\character\\character_thumb_bg\\cha_base_01_03.png",
    "dokkaninfo.com\\assets\\global\\en\\character\\thumb\\card_1022990_thumb\\card_1022990_thumb.png",
    "dokkaninfo.com\\assets\\global\\en\\layout\\en\\image\\character\\cha_type_icon_01.png",
    "dokkaninfo.com\\assets\\global\\en\\character\\thumb\\card_1023720_thumb\\card_1023720_thumb.png",
    "dokkaninfo.com\\assets\\global\\en\\character\\thumb\\card_1023730_thumb\\card_1023730_thumb.png",
    "dokkaninfo.com\\assets\\global\\en\\character\\thumb\\card_1018950_thumb\\card_1018950_thumb.png",
    "dokkaninfo.com\\assets\\global\\en\\character\\thumb\\card_1026760_thumb\\card_1026760_thumb.png",
    "dokkaninfo.com\\assets\\global\\en\\character\\thumb\\card_1026770_thumb\\card_1026770_thumb.png",
    "dokkaninfo.com\\assets\\global\\en\\layout\\en\\image\\character\\character_thumb_bg\\cha_base_00_03.png",
    "dokkaninfo.com\\assets\\global\\en\\character\\thumb\\card_1026780_thumb\\card_1026780_thumb.png",
    "dokkaninfo.com\\assets\\global\\en\\layout\\en\\image\\character\\cha_type_icon_00.png",
    "dokkaninfo.com\\assets\\global\\en\\character\\thumb\\card_1026790_thumb\\card_1026790_thumb.png",
    "dokkaninfo.com\\assets\\global\\en\\layout\\en\\image\\character\\character_thumb_bg\\cha_base_02_02.png",
    "dokkaninfo.com\\assets\\global\\en\\character\\thumb\\card_1004820_thumb\\card_1004820_thumb.png",
    "dokkaninfo.com\\assets\\global\\en\\layout\\en\\image\\character\\character_thumb_bg\\cha_base_01_02.png",
    "dokkaninfo.com\\assets\\global\\en\\character\\thumb\\card_1006270_thumb\\card_1006270_thumb.png",
    "dokkaninfo.com\\assets\\global\\en\\character\\thumb\\card_1006280_thumb\\card_1006280_thumb.png",
    "dokkaninfo.com\\assets\\global\\en\\character\\thumb\\card_1006290_thumb\\card_1006290_thumb.png",
    "dokkaninfo.com\\assets\\global\\en\\character\\thumb\\card_1006300_thumb\\card_1006300_thumb.png",
    "dokkaninfo.com\\assets\\global\\en\\layout\\en\\image\\character\\character_thumb_bg\\cha_base_04_03.png",
    "dokkaninfo.com\\assets\\global\\en\\character\\thumb\\card_1006310_thumb\\card_1006310_thumb.png",
    "dokkaninfo.com\\assets\\global\\en\\character\\thumb\\card_1006320_thumb\\card_1006320_thumb.png",
    "dokkaninfo.com\\assets\\global\\en\\character\\thumb\\card_1006640_thumb\\card_1006640_thumb.png",
    "dokkaninfo.com\\assets\\global\\en\\character\\thumb\\card_1001110_thumb\\card_1001110_thumb.png",
    "dokkaninfo.com\\assets\\global\\en\\character\\thumb\\card_1001360_thumb\\card_1001360_thumb.png",
    "dokkaninfo.com\\assets\\global\\en\\character\\thumb\\card_1000720_thumb\\card_1000720_thumb.png",
    "dokkaninfo.com\\images\\venatus.webp"
  ],
  "assets_index": {
    "site": [
      {
        "path": "dokkaninfo.com\\images\\venatus.webp",
        "category": "site",
        "subtype": "ad",
        "card_id": null,
        "locale": null,
        "note": "Ad asset"
      },
      {
        "path": "dokkaninfo.com\\images\\dokkan-info-logo.png",
        "category": "site",
        "subtype": "logo",
        "card_id": null,
        "locale": null,
        "note": "DokkanInfo branding"
      }
    ],
    "ui": [
      {
        "path": "dokkaninfo.com\\assets\\global\\en\\ingame\\common\\condition\\st_0001.png",
        "category": "ui",
        "subtype": "condition_icon",
        "card_id": null,
        "locale": null,
        "note": null
      },
      {
        "path": "dokkaninfo.com\\assets\\global\\en\\ingame\\common\\condition\\st_0002.png",
        "category": "ui",
        "subtype": "condition_icon",
        "card_id": null,
        "locale": null,
        "note": null
      },
      {
        "path": "dokkaninfo.com\\assets\\global\\en\\ingame\\common\\condition\\st_0011.png",
        "category": "ui",
        "subtype": "condition_icon",
        "card_id": null,
        "locale": null,
        "note": null
      },
      {
        "path": "dokkaninfo.com\\assets\\global\\en\\layout\\en\\image\\charamenu\\dokkan\\dok_img_kyokugen.png",
        "category": "ui",
        "subtype": "menu_icon",
        "card_id": null,
        "locale": null,
        "note": null
      },
      {
        "path": "dokkaninfo.com\\assets\\global\\en\\layout\\en\\image\\ingame\\battle\\skill_dialog\\passive_icon_st_0011.png",
        "category": "ui",
        "subtype": "passive_mark",
        "card_id": null,
        "locale": null,
        "note": null
      },
      {
        "path": "dokkaninfo.com\\assets\\global\\en\\layout\\en\\image\\ingame\\battle\\skill_dialog\\passive_icon_st_0012.png",
        "category": "ui",
        "subtype": "passive_mark",
        "card_id": null,
        "locale": null,
        "note": null
      },
      {
        "path": "dokkaninfo.com\\assets\\global\\en\\layout\\en\\image\\ingame\\battle\\skill_dialog\\passive_skill_dialog_arrow01.png",
        "category": "ui",
        "subtype": "passive_mark",
        "card_id": null,
        "locale": null,
        "note": null
      },
      {
        "path": "dokkaninfo.com\\assets\\global\\en\\layout\\en\\image\\character\\cha_rare_sm_r.png",
        "category": "ui",
        "subtype": "rarity_icon",
        "card_id": null,
        "locale": null,
        "note": null
      },
      {
        "path": "dokkaninfo.com\\assets\\global\\en\\layout\\en\\image\\character\\cha_rare_sm_sr.png",
        "category": "ui",
        "subtype": "rarity_icon",
        "card_id": null,
        "locale": null,
        "note": null
      },
      {
        "path": "dokkaninfo.com\\assets\\global\\en\\layout\\en\\image\\character\\cha_rare_sm_ssr.png",
        "category": "ui",
        "subtype": "rarity_icon",
        "card_id": null,
        "locale": null,
        "note": null
      },
      {
        "path": "dokkaninfo.com\\assets\\global\\en\\layout\\en\\image\\character\\cha_rare_sm_ur.png",
        "category": "ui",
        "subtype": "rarity_icon",
        "card_id": null,
        "locale": null,
        "note": null
      },
      {
        "path": "dokkaninfo.com\\assets\\global\\en\\layout\\en\\image\\character\\character_thumb_bg\\cha_base_00_03.png",
        "category": "ui",
        "subtype": "thumb_bg",
        "card_id": null,
        "locale": null,
        "note": null
      },
      {
        "path": "dokkaninfo.com\\assets\\global\\en\\layout\\en\\image\\character\\character_thumb_bg\\cha_base_00_04.png",
        "category": "ui",
        "subtype": "thumb_bg",
        "card_id": null,
        "locale": null,
        "note": null
      },
      {
        "path": "dokkaninfo.com\\assets\\global\\en\\layout\\en\\image\\character\\character_thumb_bg\\cha_base_01_02.png",
        "category": "ui",
        "subtype": "thumb_bg",
        "card_id": null,
        "locale": null,
        "note": null
      },
      {
        "path": "dokkaninfo.com\\assets\\global\\en\\layout\\en\\image\\character\\character_thumb_bg\\cha_base_01_03.png",
        "category": "ui",
        "subtype": "thumb_bg",
        "card_id": null,
        "locale": null,
        "note": null
      },
      {
        "path": "dokkaninfo.com\\assets\\global\\en\\layout\\en\\image\\character\\character_thumb_bg\\cha_base_01_04.png",
        "category": "ui",
        "subtype": "thumb_bg",
        "card_id": null,
        "locale": null,
        "note": null
      },
      {
        "path": "dokkaninfo.com\\assets\\global\\en\\layout\\en\\image\\character\\character_thumb_bg\\cha_base_02_02.png",
        "category": "ui",
        "subtype": "thumb_bg",
        "card_id": null,
        "locale": null,
        "note": null
      },
      {
        "path": "dokkaninfo.com\\assets\\global\\en\\layout\\en\\image\\character\\character_thumb_bg\\cha_base_02_03.png",
        "category": "ui",
        "subtype": "thumb_bg",
        "card_id": null,
        "locale": null,
        "note": null
      },
      {
        "path": "dokkaninfo.com\\assets\\global\\en\\layout\\en\\image\\character\\character_thumb_bg\\cha_base_02_04.png",
        "category": "ui",
        "subtype": "thumb_bg",
        "card_id": null,
        "locale": null,
        "note": null
      },
      {
        "path": "dokkaninfo.com\\assets\\global\\en\\layout\\en\\image\\character\\character_thumb_bg\\cha_base_03_01.png",
        "category": "ui",
        "subtype": "thumb_bg",
        "card_id": null,
        "locale": null,
        "note": null
      },
      {
        "path": "dokkaninfo.com\\assets\\global\\en\\layout\\en\\image\\character\\character_thumb_bg\\cha_base_03_03.png",
        "category": "ui",
        "subtype": "thumb_bg",
        "card_id": null,
        "locale": null,
        "note": null
      },
      {
        "path": "dokkaninfo.com\\assets\\global\\en\\layout\\en\\image\\character\\character_thumb_bg\\cha_base_03_04.png",
        "category": "ui",
        "subtype": "thumb_bg",
        "card_id": null,
        "locale": null,
        "note": null
      },
      {
        "path": "dokkaninfo.com\\assets\\global\\en\\layout\\en\\image\\character\\character_thumb_bg\\cha_base_04_01.png",
        "category": "ui",
        "subtype": "thumb_bg",
        "card_id": null,
        "locale": null,
        "note": null
      },
      {
        "path": "dokkaninfo.com\\assets\\global\\en\\layout\\en\\image\\character\\character_thumb_bg\\cha_base_04_02.png",
        "category": "ui",
        "subtype": "thumb_bg",
        "card_id": null,
        "locale": null,
        "note": null
      },
      {
        "path": "dokkaninfo.com\\assets\\global\\en\\layout\\en\\image\\character\\character_thumb_bg\\cha_base_04_03.png",
        "category": "ui",
        "subtype": "thumb_bg",
        "card_id": null,
        "locale": null,
        "note": null
      },
      {
        "path": "dokkaninfo.com\\assets\\global\\en\\layout\\en\\image\\character\\character_thumb_bg\\cha_base_04_04.png",
        "category": "ui",
        "subtype": "thumb_bg",
        "card_id": null,
        "locale": null,
        "note": null
      },
      {
        "path": "dokkaninfo.com\\assets\\global\\en\\layout\\en\\image\\character\\cha_type_icon_00.png",
        "category": "ui",
        "subtype": "type_icon",
        "card_id": null,
        "locale": null,
        "note": null
      },
      {
        "path": "dokkaninfo.com\\assets\\global\\en\\layout\\en\\image\\character\\cha_type_icon_01.png",
        "category": "ui",
        "subtype": "type_icon",
        "card_id": null,
        "locale": null,
        "note": null
      },
      {
        "path": "dokkaninfo.com\\assets\\global\\en\\layout\\en\\image\\character\\cha_type_icon_02.png",
        "category": "ui",
        "subtype": "type_icon",
        "card_id": null,
        "locale": null,
        "note": null
      },
      {
        "path": "dokkaninfo.com\\assets\\global\\en\\layout\\en\\image\\character\\cha_type_icon_03.png",
        "category": "ui",
        "subtype": "type_icon",
        "card_id": null,
        "locale": null,
        "note": null
      },
      {
        "path": "dokkaninfo.com\\assets\\global\\en\\layout\\en\\image\\character\\cha_type_icon_04.png",
        "category": "ui",
        "subtype": "type_icon",
        "card_id": null,
        "locale": null,
        "note": null
      },
      {
        "path": "dokkaninfo.com\\assets\\global\\en\\layout\\en\\image\\character\\cha_type_icon_20.png",
        "category": "ui",
        "subtype": "type_icon",
        "card_id": null,
        "locale": null,
        "note": null
      },
      {
        "path": "dokkaninfo.com\\assets\\global\\en\\layout\\en\\image\\character\\cha_type_icon_21.png",
        "category": "ui",
        "subtype": "type_icon",
        "card_id": null,
        "locale": null,
        "note": null
      },
      {
        "path": "dokkaninfo.com\\assets\\global\\en\\layout\\en\\image\\character\\cha_type_icon_22.png",
        "category": "ui",
        "subtype": "type_icon",
        "card_id": null,
        "locale": null,
        "note": null
      },
      {
        "path": "dokkaninfo.com\\assets\\global\\en\\layout\\en\\image\\character\\cha_type_icon_23.png",
        "category": "ui",
        "subtype": "type_icon",
        "card_id": null,
        "locale": null,
        "note": null
      },
      {
        "path": "dokkaninfo.com\\assets\\global\\en\\layout\\en\\image\\character\\cha_type_icon_24.png",
        "category": "ui",
        "subtype": "type_icon",
        "card_id": null,
        "locale": null,
        "note": null
      }
    ],
    "thumbnail": [
      {
        "path": "dokkaninfo.com\\assets\\global\\en\\character\\thumb\\card_1000510_thumb\\card_1000510_thumb.png",
        "category": "thumbnail",
        "subtype": "card_thumb",
        "card_id": "1000510",
        "locale": "en",
        "note": null
      },
      {
        "path": "dokkaninfo.com\\assets\\global\\en\\character\\thumb\\card_1000720_thumb\\card_1000720_thumb.png",
        "category": "thumbnail",
        "subtype": "card_thumb",
        "card_id": "1000720",
        "locale": "en",
        "note": null
      },
      {
        "path": "dokkaninfo.com\\assets\\global\\en\\character\\thumb\\card_1001050_thumb\\card_1001050_thumb.png",
        "category": "thumbnail",
        "subtype": "card_thumb",
        "card_id": "1001050",
        "locale": "en",
        "note": null
      },
      {
        "path": "dokkaninfo.com\\assets\\global\\en\\character\\thumb\\card_1001110_thumb\\card_1001110_thumb.png",
        "category": "thumbnail",
        "subtype": "card_thumb",
        "card_id": "1001110",
        "locale": "en",
        "note": null
      },
      {
        "path": "dokkaninfo.com\\assets\\global\\en\\character\\thumb\\card_1001290_thumb\\card_1001290_thumb.png",
        "category": "thumbnail",
        "subtype": "card_thumb",
        "card_id": "1001290",
        "locale": "en",
        "note": null
      },
      {
        "path": "dokkaninfo.com\\assets\\global\\en\\character\\thumb\\card_1001360_thumb\\card_1001360_thumb.png",
        "category": "thumbnail",
        "subtype": "card_thumb",
        "card_id": "1001360",
        "locale": "en",
        "note": null
      },
      {
        "path": "dokkaninfo.com\\assets\\global\\en\\character\\thumb\\card_1004820_thumb\\card_1004820_thumb.png",
        "category": "thumbnail",
        "subtype": "card_thumb",
        "card_id": "1004820",
        "locale": "en",
        "note": null
      },
      {
        "path": "dokkaninfo.com\\assets\\global\\en\\character\\thumb\\card_1006270_thumb\\card_1006270_thumb.png",
        "category": "thumbnail",
        "subtype": "card_thumb",
        "card_id": "1006270",
        "locale": "en",
        "note": null
      },
      {
        "path": "dokkaninfo.com\\assets\\global\\en\\character\\thumb\\card_1006280_thumb\\card_1006280_thumb.png",
        "category": "thumbnail",
        "subtype": "card_thumb",
        "card_id": "1006280",
        "locale": "en",
        "note": null
      },
      {
        "path": "dokkaninfo.com\\assets\\global\\en\\character\\thumb\\card_1006290_thumb\\card_1006290_thumb.png",
        "category": "thumbnail",
        "subtype": "card_thumb",
        "card_id": "1006290",
        "locale": "en",
        "note": null
      },
      {
        "path": "dokkaninfo.com\\assets\\global\\en\\character\\thumb\\card_1006300_thumb\\card_1006300_thumb.png",
        "category": "thumbnail",
        "subtype": "card_thumb",
        "card_id": "1006300",
        "locale": "en",
        "note": null
      },
      {
        "path": "dokkaninfo.com\\assets\\global\\en\\character\\thumb\\card_1006310_thumb\\card_1006310_thumb.png",
        "category": "thumbnail",
        "subtype": "card_thumb",
        "card_id": "1006310",
        "locale": "en",
        "note": null
      },
      {
        "path": "dokkaninfo.com\\assets\\global\\en\\character\\thumb\\card_1006320_thumb\\card_1006320_thumb.png",
        "category": "thumbnail",
        "subtype": "card_thumb",
        "card_id": "1006320",
        "locale": "en",
        "note": null
      },
      {
        "path": "dokkaninfo.com\\assets\\global\\en\\character\\thumb\\card_1006640_thumb\\card_1006640_thumb.png",
        "category": "thumbnail",
        "subtype": "card_thumb",
        "card_id": "1006640",
        "locale": "en",
        "note": null
      },
      {
        "path": "dokkaninfo.com\\assets\\global\\en\\character\\thumb\\card_1018950_thumb\\card_1018950_thumb.png",
        "category": "thumbnail",
        "subtype": "card_thumb",
        "card_id": "1018950",
        "locale": "en",
        "note": null
      },
      {
        "path": "dokkaninfo.com\\assets\\global\\en\\character\\thumb\\card_1022990_thumb\\card_1022990_thumb.png",
        "category": "thumbnail",
        "subtype": "card_thumb",
        "card_id": "1022990",
        "locale": "en",
        "note": null
      },
      {
        "path": "dokkaninfo.com\\assets\\global\\en\\character\\thumb\\card_1023000_thumb\\card_1023000_thumb.png",
        "category": "thumbnail",
        "subtype": "card_thumb",
        "card_id": "1023000",
        "locale": "en",
        "note": null
      },
      {
        "path": "dokkaninfo.com\\assets\\global\\en\\character\\thumb\\card_1023720_thumb\\card_1023720_thumb.png",
        "category": "thumbnail",
        "subtype": "card_thumb",
        "card_id": "1023720",
        "locale": "en",
        "note": null
      },
      {
        "path": "dokkaninfo.com\\assets\\global\\en\\character\\thumb\\card_1023730_thumb\\card_1023730_thumb.png",
        "category": "thumbnail",
        "subtype": "card_thumb",
        "card_id": "1023730",
        "locale": "en",
        "note": null
      },
      {
        "path": "dokkaninfo.com\\assets\\global\\en\\character\\thumb\\card_1023740_thumb\\card_1023740_thumb.png",
        "category": "thumbnail",
        "subtype": "card_thumb",
        "card_id": "1023740",
        "locale": "en",
        "note": null
      },
      {
        "path": "dokkaninfo.com\\assets\\global\\en\\character\\thumb\\card_1023750_thumb\\card_1023750_thumb.png",
        "category": "thumbnail",
        "subtype": "card_thumb",
        "card_id": "1023750",
        "locale": "en",
        "note": null
      },
      {
        "path": "dokkaninfo.com\\assets\\global\\en\\character\\thumb\\card_1023770_thumb\\card_1023770_thumb.png",
        "category": "thumbnail",
        "subtype": "card_thumb",
        "card_id": "1023770",
        "locale": "en",
        "note": null
      },
      {
        "path": "dokkaninfo.com\\assets\\global\\en\\character\\thumb\\card_1026760_thumb\\card_1026760_thumb.png",
        "category": "thumbnail",
        "subtype": "card_thumb",
        "card_id": "1026760",
        "locale": "en",
        "note": null
      },
      {
        "path": "dokkaninfo.com\\assets\\global\\en\\character\\thumb\\card_1026770_thumb\\card_1026770_thumb.png",
        "category": "thumbnail",
        "subtype": "card_thumb",
        "card_id": "1026770",
        "locale": "en",
        "note": null
      },
      {
        "path": "dokkaninfo.com\\assets\\global\\en\\character\\thumb\\card_1026780_thumb\\card_1026780_thumb.png",
        "category": "thumbnail",
        "subtype": "card_thumb",
        "card_id": "1026780",
        "locale": "en",
        "note": null
      },
      {
        "path": "dokkaninfo.com\\assets\\global\\en\\character\\thumb\\card_1026790_thumb\\card_1026790_thumb.png",
        "category": "thumbnail",
        "subtype": "card_thumb",
        "card_id": "1026790",
        "locale": "en",
        "note": null
      },
      {
        "path": "dokkaninfo.com\\assets\\global\\en\\character\\thumb\\card_1028570_thumb\\card_1028570_thumb.png",
        "category": "thumbnail",
        "subtype": "card_thumb",
        "card_id": "1028570",
        "locale": "en",
        "note": null
      },
      {
        "path": "dokkaninfo.com\\assets\\global\\en\\character\\thumb\\card_1028580_thumb\\card_1028580_thumb.png",
        "category": "thumbnail",
        "subtype": "card_thumb",
        "card_id": "1028580",
        "locale": "en",
        "note": null
      },
      {
        "path": "dokkaninfo.com\\assets\\global\\en\\character\\thumb\\card_1028590_thumb\\card_1028590_thumb.png",
        "category": "thumbnail",
        "subtype": "card_thumb",
        "card_id": "1028590",
        "locale": "en",
        "note": null
      },
      {
        "path": "dokkaninfo.com\\assets\\global\\en\\character\\thumb\\card_1029580_thumb\\card_1029580_thumb.png",
        "category": "thumbnail",
        "subtype": "card_thumb",
        "card_id": "1029580",
        "locale": "en",
        "note": null
      },
      {
        "path": "dokkaninfo.com\\assets\\global\\en\\character\\thumb\\card_1029590_thumb\\card_1029590_thumb.png",
        "category": "thumbnail",
        "subtype": "card_thumb",
        "card_id": "1029590",
        "locale": "en",
        "note": null
      },
      {
        "path": "dokkaninfo.com\\assets\\global\\en\\character\\thumb\\card_1031300_thumb\\card_1031300_thumb.png",
        "category": "thumbnail",
        "subtype": "card_thumb",
        "card_id": "1031300",
        "locale": "en",
        "note": null
      }
    ],
    "card_art": [
      {
        "path": "dokkaninfo.com\\assets\\global\\en\\character\\card\\1029580\\card_1029580_bg.png",
        "category": "card_art",
        "subtype": "bg",
        "card_id": "1029580",
        "locale": "en",
        "note": null
      },
      {
        "path": "dokkaninfo.com\\assets\\global\\en\\character\\card\\1029580\\card_1029580_piece.png",
        "category": "card_art",
        "subtype": "card_asset",
        "card_id": "1029580",
        "locale": "en",
        "note": null
      },
      {
        "path": "dokkaninfo.com\\assets\\global\\en\\character\\card\\1029580\\card_1029580_character.png",
        "category": "card_art",
        "subtype": "character",
        "card_id": "1029580",
        "locale": "en",
        "note": null
      },
      {
        "path": "dokkaninfo.com\\assets\\global\\en\\character\\card\\1029580\\card_1029580_circle.png",
        "category": "card_art",
        "subtype": "circle",
        "card_id": "1029580",
        "locale": "en",
        "note": null
      },
      {
        "path": "dokkaninfo.com\\assets\\global\\en\\character\\card\\1029580\\card_1029580_cutin.png",
        "category": "card_art",
        "subtype": "cutin",
        "card_id": "1029580",
        "locale": "en",
        "note": null
      },
      {
        "path": "dokkaninfo.com\\assets\\global\\en\\character\\card\\1029580\\card_1029580sp_cutin_1.png",
        "category": "card_art",
        "subtype": "cutin",
        "card_id": "1029580",
        "locale": "en",
        "note": null
      },
      {
        "path": "dokkaninfo.com\\assets\\global\\en\\character\\card\\1029580\\card_1029580_effect.png",
        "category": "card_art",
        "subtype": "effect",
        "card_id": "1029580",
        "locale": "en",
        "note": null
      },
      {
        "path": "dokkaninfo.com\\assets\\global\\en\\character\\card\\1029580\\1029580.png",
        "category": "card_art",
        "subtype": "full_card",
        "card_id": "1029580",
        "locale": "en",
        "note": null
      },
      {
        "path": "dokkaninfo.com\\assets\\global\\en\\character\\card\\1029580\\en\\card_1029580_sp_name.png",
        "category": "card_art",
        "subtype": "super_name",
        "card_id": "1029580",
        "locale": "en",
        "note": null
      },
      {
        "path": "dokkaninfo.com\\assets\\global\\en\\character\\card\\1029580\\en\\card_1029580_sp_phrase.png",
        "category": "card_art",
        "subtype": "super_phrase",
        "card_id": "1029580",
        "locale": "en",
        "note": null
      }
    ],
    "other": [
      {
        "path": "dokkaninfo.com\\assets\\global\\en\\ingame\\banners\\gasha_top_banner_11094.png",
        "category": "other",
        "subtype": null,
        "card_id": null,
        "locale": "en",
        "note": null
      },
      {
        "path": "dokkaninfo.com\\assets\\global\\en\\ingame\\banners\\gasha_top_banner_11124.png",
        "category": "other",
        "subtype": null,
        "card_id": null,
        "locale": "en",
        "note": null
      },
      {
        "path": "dokkaninfo.com\\assets\\global\\en\\item\\awaken\\en\\thumb\\thumb_awaken_items_00003\\thumb_awaken_items_00003.png",
        "category": "other",
        "subtype": null,
        "card_id": null,
        "locale": "en",
        "note": null
      },
      {
        "path": "dokkaninfo.com\\assets\\global\\en\\item\\awaken\\en\\thumb\\thumb_awaken_items_00005\\thumb_awaken_items_00005.png",
        "category": "other",
        "subtype": null,
        "card_id": null,
        "locale": "en",
        "note": null
      },
      {
        "path": "dokkaninfo.com\\assets\\global\\en\\item\\awaken\\en\\thumb\\thumb_awaken_items_00009\\thumb_awaken_items_00009.png",
        "category": "other",
        "subtype": null,
        "card_id": null,
        "locale": "en",
        "note": null
      },
      {
        "path": "dokkaninfo.com\\assets\\global\\en\\item\\awaken\\en\\thumb\\thumb_awaken_items_00015\\thumb_awaken_items_00015.png",
        "category": "other",
        "subtype": null,
        "card_id": null,
        "locale": "en",
        "note": null
      },
      {
        "path": "dokkaninfo.com\\assets\\global\\en\\item\\awaken\\en\\thumb\\thumb_awaken_items_00020\\thumb_awaken_items_00020.png",
        "category": "other",
        "subtype": null,
        "card_id": null,
        "locale": "en",
        "note": null
      },
      {
        "path": "dokkaninfo.com\\assets\\global\\en\\item\\awaken\\en\\thumb\\thumb_awaken_items_15081\\thumb_awaken_items_15081.png",
        "category": "other",
        "subtype": null,
        "card_id": null,
        "locale": "en",
        "note": null
      },
      {
        "path": "dokkaninfo.com\\assets\\global\\en\\layout\\en\\image\\item\\awaken\\awaken_thumb_bg\\thumb_awaken_bronze.png",
        "category": "other",
        "subtype": null,
        "card_id": null,
        "locale": "en",
        "note": null
      },
      {
        "path": "dokkaninfo.com\\assets\\global\\en\\layout\\en\\image\\item\\awaken\\awaken_thumb_bg\\thumb_awaken_gold.png",
        "category": "other",
        "subtype": null,
        "card_id": null,
        "locale": "en",
        "note": null
      },
      {
        "path": "dokkaninfo.com\\assets\\global\\en\\layout\\en\\image\\item\\awaken\\awaken_thumb_bg\\thumb_awaken_rainbow.png",
        "category": "other",
        "subtype": null,
        "card_id": null,
        "locale": "en",
        "note": null
      },
      {
        "path": "dokkaninfo.com\\assets\\global\\en\\layout\\en\\image\\item\\awaken\\awaken_thumb_bg\\thumb_awaken_silver.png",
        "category": "other",
        "subtype": null,
        "card_id": null,
        "locale": "en",
        "note": null
      },
      {
        "path": "dokkaninfo.com\\assets\\global\\en\\outgame\\extension\\character_detail\\en\\character_detail\\sp_skill_icon_01.png",
        "category": "other",
        "subtype": null,
        "card_id": null,
        "locale": "en",
        "note": null
      }
    ],
    "event_banner": [
      {
        "path": "dokkaninfo.com\\assets\\global\\en\\ingame\\events\\myp_banner_event_zbattle_003.png",
        "category": "event_banner",
        "subtype": "zbattle",
        "card_id": null,
        "locale": "en",
        "note": null
      },
      {
        "path": "dokkaninfo.com\\assets\\global\\en\\ingame\\events\\myp_banner_event_zbattle_004.png",
        "category": "event_banner",
        "subtype": "zbattle",
        "card_id": null,
        "locale": "en",
        "note": null
      },
      {
        "path": "dokkaninfo.com\\assets\\global\\en\\ingame\\events\\myp_banner_event_zbattle_062.png",
        "category": "event_banner",
        "subtype": "zbattle",
        "card_id": null,
        "locale": "en",
        "note": null
      },
      {
        "path": "dokkaninfo.com\\assets\\global\\en\\ingame\\events\\myp_banner_event_zbattle_067.png",
        "category": "event_banner",
        "subtype": "zbattle",
        "card_id": null,
        "locale": "en",
        "note": null
      },
      {
        "path": "dokkaninfo.com\\assets\\global\\en\\ingame\\events\\myp_banner_event_zbattle_078.png",
        "category": "event_banner",
        "subtype": "zbattle",
        "card_id": null,
        "locale": "en",
        "note": null
      },
      {
        "path": "dokkaninfo.com\\assets\\global\\en\\ingame\\events\\myp_banner_event_zbattle_090.png",
        "category": "event_banner",
        "subtype": "zbattle",
        "card_id": null,
        "locale": "en",
        "note": null
      },
      {
        "path": "dokkaninfo.com\\assets\\global\\en\\ingame\\events\\myp_banner_event_zbattle_134.png",
        "category": "event_banner",
        "subtype": "zbattle",
        "card_id": null,
        "locale": "en",
        "note": null
      },
      {
        "path": "dokkaninfo.com\\assets\\global\\en\\ingame\\events\\myp_banner_event_zbattle_138.png",
        "category": "event_banner",
        "subtype": "zbattle",
        "card_id": null,
        "locale": "en",
        "note": null
      },
      {
        "path": "dokkaninfo.com\\assets\\global\\en\\ingame\\events\\myp_banner_event_zbattle_166.png",
        "category": "event_banner",
        "subtype": "zbattle",
        "card_id": null,
        "locale": "en",
        "note": null
      },
      {
        "path": "dokkaninfo.com\\assets\\global\\en\\ingame\\events\\myp_banner_event_zbattle_172.png",
        "category": "event_banner",
        "subtype": "zbattle",
        "card_id": null,
        "locale": "en",
        "note": null
      },
      {
        "path": "dokkaninfo.com\\assets\\global\\en\\ingame\\events\\myp_banner_event_zbattle_177.png",
        "category": "event_banner",
        "subtype": "zbattle",
        "card_id": null,
        "locale": "en",
        "note": null
      },
      {
        "path": "dokkaninfo.com\\assets\\global\\en\\ingame\\events\\myp_banner_event_zbattle_182.png",
        "category": "event_banner",
        "subtype": "zbattle",
        "card_id": null,
        "locale": "en",
        "note": null
      }
    ],
    "category_label": [
      {
        "path": "dokkaninfo.com\\assets\\global\\en\\card_category\\label\\card_category_label_0014_b_on.png",
        "category": "category_label",
        "subtype": "0014",
        "card_id": null,
        "locale": "en",
        "note": null
      },
      {
        "path": "dokkaninfo.com\\assets\\global\\en\\card_category\\label\\card_category_label_0041_b_on.png",
        "category": "category_label",
        "subtype": "0041",
        "card_id": null,
        "locale": "en",
        "note": null
      },
      {
        "path": "dokkaninfo.com\\assets\\global\\en\\card_category\\label\\card_category_label_0062_b_on.png",
        "category": "category_label",
        "subtype": "0062",
        "card_id": null,
        "locale": "en",
        "note": null
      },
      {
        "path": "dokkaninfo.com\\assets\\global\\en\\card_category\\label\\card_category_label_0097_b_on.png",
        "category": "category_label",
        "subtype": "0097",
        "card_id": null,
        "locale": "en",
        "note": null
      }
    ]
  }
}